tenor_dl/tenor_dl.py
tenor_dl-0.2.1.dist-info/entry_points.txt
tenor_dl-0.2.1.dist-info/LICENSE
tenor_dl-0.2.1.dist-info/WHEEL
tenor_dl-0.2.1.dist-info/METADATA
tenor_dl-0.2.1.dist-info/RECORD
