Metadata-Version: 2.1
Name: tenor-dl
Version: 0.2.1
Summary: simple CLI script to easily download gifs from tenor.com
License: WTFPL
Author: zocker-160
Author-email: zocker1600@posteo.net
Requires-Python: >=3.8,<4.0
Classifier: License :: Other/Proprietary License
Classifier: Programming Language :: Python :: 3
Classifier: Programming Language :: Python :: 3.10
Classifier: Programming Language :: Python :: 3.8
Classifier: Programming Language :: Python :: 3.9
Requires-Dist: pyquery (>=1.4.3,<2.0.0)
Requires-Dist: requests (>=2.28.1,<3.0.0)
